aiida_abinit/__init__.py
aiida_abinit/calculations.py
aiida_abinit/parsers.py
aiida_abinit/utils/__init__.py
aiida_abinit/utils/dictionary.py
aiida_abinit/utils/kpoints.py
aiida_abinit/utils/pseudos.py
aiida_abinit/utils/resources.py
aiida_abinit/workflows/__init__.py
aiida_abinit/workflows/base.py
aiida_abinit-0.5.0.dist-info/entry_points.txt
aiida_abinit-0.5.0.dist-info/LICENSE.txt
aiida_abinit-0.5.0.dist-info/WHEEL
aiida_abinit-0.5.0.dist-info/METADATA
aiida_abinit-0.5.0.dist-info/RECORD
