Metadata-Version: 2.1
Name: aiida-abinit
Version: 0.5.0
Summary: The AiiDA plugin for ABINIT.
Keywords: aiida,abinit
Author-email: Samuel Ponce <samuel.pon@gmail.com>
Requires-Python: >=3.8
Classifier: Development Status :: 4 - Beta
Classifier: Framework :: AiiDA
Classifier: License :: OSI Approved :: MIT License
Classifier: Operating System :: POSIX :: Linux
Classifier: Operating System :: MacOS :: MacOS X
Classifier: Programming Language :: Python
Classifier: Programming Language :: Python :: 3.8
Classifier: Programming Language :: Python :: 3.9
Classifier: Programming Language :: Python :: 3.10
Classifier: Programming Language :: Python :: 3.11
Requires-Dist: aiida_core[atomic_tools]~=2.0
Requires-Dist: aiida-pseudo~=1.0
Requires-Dist: abipy>=0.8.0
Requires-Dist: packaging
Requires-Dist: pymatgen<=v2023.9.10
Requires-Dist: numpy
Requires-Dist: importlib_resources
Requires-Dist: sphinx ; extra == "docs"
Requires-Dist: docutils ; extra == "docs"
Requires-Dist: sphinx-copybutton~=0.3.0 ; extra == "docs"
Requires-Dist: sphinx-book-theme~=0.1.0 ; extra == "docs"
Requires-Dist: sphinx-click~=2.7.1 ; extra == "docs"
Requires-Dist: pre-commit~=2.2 ; extra == "pre-commit"
Requires-Dist: pylint==2.6.0 ; extra == "pre-commit"
Requires-Dist: pgtest~=1.3 ; extra == "tests"
Requires-Dist: pytest~=7.2 ; extra == "tests"
Requires-Dist: pytest-regressions~=1.0 ; extra == "tests"
Project-URL: Home, https://github.com/sponce24/aiida-abinit
Project-URL: Source, https://github.com/sponce24/aiida-abinit
Provides-Extra: docs
Provides-Extra: pre-commit
Provides-Extra: tests
